<?xml version="1.0" encoding="UTF-8"?>
<main><node id="1" name="体力药剂（小）x1" item_type="item" item_id="1010" item_num="1" price_type="gongxian" price="100" limit="4" shangchen_lv="0" weight="10"/><node id="2" name="绿色钥匙x1" item_type="baoshi" item_id="1" item_num="1" price_type="gongxian" price="160" limit="3" shangchen_lv="0" weight="10"/><node id="4" name="绿色宝箱x1" item_type="item" item_id="2001" item_num="1" price_type="gongxian" price="240" limit="3" shangchen_lv="0" weight="20"/><node id="5" name="体力药剂（中）x1" item_type="item" item_id="1102" item_num="1" price_type="gongxian" price="140" limit="4" shangchen_lv="0" weight="10"/><node id="6" name="三星经验卡x1" item_type="item" item_id="1103" item_num="1" price_type="gongxian" price="480" limit="3" shangchen_lv="0" weight="10"/><node id="7" name="蓝色钥匙x1" item_type="item" item_id="1104" item_num="1" price_type="gongxian" price="100" limit="3" shangchen_lv="0" weight="10"/><node id="8" name="兽魂丹x1" item_type="item" item_id="1105" item_num="1" price_type="gongxian" price="3600" limit="2" shangchen_lv="0" weight="10"/><node id="9" name="突破丹x1" item_type="item" item_id="1106" item_num="1" price_type="gongxian" price="3600" limit="2" shangchen_lv="0" weight="10"/><node id="10" name="洗练石x1" item_type="item" item_id="1107" item_num="1" price_type="gongxian" price="480" limit="4" shangchen_lv="0" weight="10"/><node id="11" name="技能经验银书x1" item_type="item" item_id="1108" item_num="1" price_type="gongxian" price="390" limit="5" shangchen_lv="0" weight="10"/><node id="12" name="四星经验卡x1" item_type="item" item_id="1109" item_num="1" price_type="gongxian" price="480" limit="5" shangchen_lv="0" weight="10"/></main>
